Workbook
Name CurrentQuarter: 'PQ Staging'!$A$5

Sheet Cover
B2: McDonald's Corporation
B3: Franchise vs. Company-Operated Margin Bridge, 3-Statement Model and Valuation
B4: Prepared by Kaushal Jaiswal
B6: Contents
B7: 3-Statement Model | C7: Income Statement, Balance Sheet, and Cash Flow Statement, linked and tying out.
B8: Supporting Schedules | C8: Working capital, debt, and property and equipment roll-forwards feeding the statements above.
B9: Segment and Margin Analysis | C9: Segment-level revenue and margin, and the mix versus rate decomposition behind the margin change.
B10: Valuation | C10: Cost of capital build, five-year DCF, and a sensitivity grid across WACC and terminal growth.
B11: PQ Staging | C11: Quarterly data staging area for the Power Query refresh pipeline.
B12: Power BI Source Data | C12: Clean, linked tables feeding the Power BI dashboard.
B14: Conventions
B15: Blue text | C15: Hardcoded input from a McDonald's SEC filing or earnings release.
B16: Black text | C16: Formula calculated within the same tab.
B17: Green text | C17: Formula linked from another tab in this workbook.
B18: Tie-out checks | C18: Shown inline within each statement, computing to zero where the underlying logic requires it.
B20: Sources
B21: - McDonald's Corporation Form 10-K, fiscal year ended December 31, 2025, filed February 24, 2026 (SEC EDGAR, CIK 0000063908)
B22: - McDonald's Corporation Q4 2025 earnings release, Exhibit 99.1

Sheet 3-Statement Model
A1: McDonald's Corporation, Consolidated Financial Statements
A2: $ in millions, except per-share data. Source: FY2025 Form 10-K and Q4 2025 earnings release, Exhibit 99.1.
A3: This tab covers, in order: Income Statement, Balance Sheet, Cash Flow Statement. Click column J, then use Ctrl+Down or Ctrl+Up to jump to each blue X marker, which sits on that section's header row.
A6: Income Statement | J6: X
B8: FY2023 | C8: FY2024 | D8: FY2025 | E8: FY25 vs FY24
A9: Revenues
A10: Revenues from franchised restaurants | B10: 15437 | C10: 15715 | D10: 16548
A11: Sales by company-operated restaurants | B11: 9742 | C11: 9782 | D11: 9690
A12: Other revenues | B12: 316 | C12: 423 | D12: 647
A13: Total revenues | B13: =SUM(B10:B12) -> 25495 | C13: =SUM(C10:C12) -> 25920 | D13: =SUM(D10:D12) -> 26885 | E13: =D13/C13-1 -> 0.037229938
A15: Operating costs and expenses
A16: Franchised restaurants, occupancy expenses | B16: 2475 | C16: 2536 | D16: 2618
A17: Company-operated restaurant expenses | B17: 8224 | C17: 8334 | D17: 8268
A18: Other restaurant expenses | B18: 232 | C18: 339 | D18: 564
A19: SG&A, depreciation and amortization | B19: 382 | C19: 447 | D19: 457
A20: SG&A, other | B20: 2435 | C20: 2412 | D20: 2583
A21: Other operating (income) expense, net | B21: 99 | C21: 139 | D21: 2
A22: Total operating costs and expenses | B22: =SUM(B16:B21) -> 13847 | C22: =SUM(C16:C21) -> 14207 | D22: =SUM(D16:D21) -> 14492
A24: Operating income | B24: =B13-B22 -> 11648 | C24: =C13-C22 -> 11713 | D24: =D13-D22 -> 12393 | E24: =D24/C24-1 -> 0.058055152
A26: Interest expense | B26: 1361 | C26: 1506 | D26: 1582
A27: Nonoperating (income) expense, net | B27: -236 | C27: -139 | D27: -87
A28: Income before provision for income taxes | B28: =B24-B26-B27 -> 10523 | C28: =C24-C26-C27 -> 10346 | D28: =D24-D26-D27 -> 10898
A30: Provision for income taxes | B30: 2053 | C30: 2121 | D30: 2334
A31: Net income | B31: =B28-B30 -> 8470 | C31: =C28-C30 -> 8225 | D31: =D28-D30 -> 8564 | E31: =D31/C31-1 -> 0.041215805
A33: Operating margin | B33: =B24/B13 -> 0.4568739 | C33: =C24/C13 -> 0.45189043 | D33: =D24/D13 -> 0.46096336
A34: Net margin | B34: =B31/B13 -> 0.332222 | C34: =C31/C13 -> 0.31732253 | D34: =D31/D13 -> 0.31854194
A35: Diluted EPS | B35: 11.56 | C35: 11.39 | D35: 11.95
A40: Balance Sheet | J40: X
B42: FY2024 | C42: FY2025
A43: Assets
A44: Cash and equivalents | B44: 1085 | C44: 774
A45: Accounts and notes receivable | B45: 2383 | C45: 2466
A46: Other current assets | B46: 1130 | C46: 924
A47: Total current assets | B47: =SUM(B44:B46) -> 4598 | C47: =SUM(C44:C46) -> 4164
A49: Total other assets | B49: 11950 | C49: 12505
A50: Lease right-of-use asset, net | B50: 13339 | C50: 14606
A51: Net property and equipment | B51: 25295 | C51: 28241
A52: Total assets | B52: =B47+B49+B50+B51 -> 55182 | C52: =C47+C49+C50+C51 -> 59516
A54: Liabilities and shareholders' equity
A55: Total current liabilities | B55: 3861 | C55: 4361
A56: Long-term debt | B56: 38424 | C56: 39973
A57: Long-term lease liability | B57: 12888 | C57: 14147
A58: Other long-term liabilities | B58: 1893 | C58: 1788
A59: Deferred income taxes | B59: 1914 | C59: 1038
A60: Total liabilities | B60: =SUM(B55:B59) -> 58980 | C60: =SUM(C55:C59) -> 61307
A62: Total shareholders' equity (deficit) | B62: =B52-B60 -> -3798 | C62: =C52-C60 -> -1791
A64: Tie-out: total assets less total liabilities and equity | C64: =B52-(B60+B62) -> 0 | D64: =C52-(C60+C62) -> 0
A70: Cash Flow Statement | J70: X
B72: FY2024 | C72: FY2025
A73: Operating activities
A74: Net income | B74: =C31 -> 8225 | C74: =D31 -> 8564
A75: Changes in working capital items | B75: -437 | C75: 106
A76: Other operating adjustments, including depreciation | B76: 1660 | C76: 1882
A77: Cash provided by operations | B77: =SUM(B74:B76) -> 9448 | C77: =SUM(C74:C76) -> 10552
A79: Investing activities
A80: Capital expenditures | B80: -2775 | C80: -3365
A81: Sales and purchases of restaurant businesses and property | B81: -2073 | C81: 122
A82: Other investing | B82: -498 | C82: -579
A83: Cash used for investing | B83: =SUM(B80:B82) -> -5346 | C83: =SUM(C80:C82) -> -3822
A85: Financing activities
A86: Net short-term borrowings and long-term financing | B86: -72 | C86: -73
A87: Treasury stock purchases | B87: -2824 | C87: -2056
A88: Common stock dividends | B88: -4870 | C88: -5115
A89: Proceeds from stock option exercises and other | B89: 271 | C89: 118
A90: Cash used for financing | B90: =SUM(B86:B89) -> -7495 | C90: =SUM(C86:C89) -> -7126
A92: Effect of exchange rates on cash | B92: -101 | C92: 86
A93: Net change in cash | B93: =B77+B83+B90+B92 -> -3494 | C93: =C77+C83+C90+C92 -> -310
A95: Cash at beginning of year | B95: 4579 | C95: =B96 -> 1085
A96: Cash at end of year | B96: =B95+B93 -> 1085 | C96: =C95+C93 -> 775
A98: Free cash flow (operating cash flow less capital expenditures) | B98: =B77+B80 -> 6673 | C98: =C77+C80 -> 7187
A100: Tie-out: cash flow ending cash less balance sheet cash | C100: =C96-C44 -> 1

Sheet Supporting Schedules
A1: McDonald's Corporation, Supporting Schedules
A2: $ in millions. Feeds the 3-Statement Model tab.
A3: This tab covers, in order: Working Capital, Debt Schedule, PP&E Rollforward. Click column J, then use Ctrl+Down or Ctrl+Up to jump to each blue X marker, which sits on that section's header row.
A6: Working Capital | J6: X
B8: FY2024 | C8: FY2025
A9: Working capital components, linked from the 3-Statement Model tab
A10: Accounts and notes receivable | B10: ='3-Statement Model'!B45 -> 2383 | C10: ='3-Statement Model'!C45 -> 2466
A11: Other current assets | B11: ='3-Statement Model'!B46 -> 1130 | C11: ='3-Statement Model'!C46 -> 924
A12: Total current liabilities | B12: ='3-Statement Model'!B55 -> 3861 | C12: ='3-Statement Model'!C55 -> 4361
A13: Net working capital, excluding cash | B13: =B10+B11-B12 -> -348 | C13: =C10+C11-C12 -> -971
A15: Change in net working capital | C15: =C13-B13 -> -623
A16: Reported change in working capital (Cash Flow Statement) | C16: ='3-Statement Model'!C75 -> 106
A17: Variance versus this schedule's simplified calculation | C17: =C16-(-C15) -> -517
A30: Debt Schedule | J30: X
B32: FY2024 | C32: FY2025
A33: Debt balance roll-forward
A34: Long-term debt, beginning of year | B34: 35800 | C34: =B36 -> 38424
A35: Net issuances | B35: 2624 | C35: 1549
A36: Long-term debt, end of year | B36: =B34+B35 -> 38424 | C36: =C34+C35 -> 39973
A38: Tie-out: ties to 3-Statement Model long-term debt | C38: =C36-'3-Statement Model'!C56 -> 0
A40: Interest expense build
A41: Weighted-average interest rate on total debt | B41: 0.04 | C41: 0.04
A42: Average debt balance | B42: =(B34+B36)/2 -> 37112 | C42: =(C34+C36)/2 -> 39198.5
A43: Implied interest expense | B43: =B42*B41 -> 1484.48 | C43: =C42*C41 -> 1567.94
A44: Actual interest expense, per the 3-Statement Model tab | B44: ='3-Statement Model'!B26 -> 1361 | C44: ='3-Statement Model'!C26 -> 1506
A45: Variance, reflecting fees, swaps, and the mix of fixed versus floating-rate debt | B45: =B44-B43 -> -123.48 | C45: =C44-C43 -> -61.94
A47: Credit profile
A48: S&P / Moody's rating | B48: BBB+ / Baa1 | C48: BBB+ / Baa1
A49: Cash from operations to total debt | B49: ='3-Statement Model'!B77/B36 -> 0.24588799 | C49: ='3-Statement Model'!C77/C36 -> 0.26397819
A55: PP&E Rollforward | J55: X
B57: FY2024 | C57: FY2025
A58: Net PP&E roll-forward
A59: Net PP&E, beginning of year | B59: 23697 | C59: ='3-Statement Model'!B51 -> 25295
A60: Add, capital expenditures | B60: =-'3-Statement Model'!B80 -> 2775 | C60: =-'3-Statement Model'!C80 -> 3365
A61: Less, depreciation and amortization | B61: ='3-Statement Model'!B19 -> 382 | C61: ='3-Statement Model'!C19 -> 447
A62: Other, including foreign exchange and restaurant-level depreciation | B62: ='3-Statement Model'!B51-(B59+B60-B61) -> -795 | C62: ='3-Statement Model'!C51-(C59+C60-C61) -> 28
A63: Net PP&E, end of year | B63: =B59+B60-B61+B62 -> 25295 | C63: =C59+C60-C61+C62 -> 28241
A65: Tie-out: ties to 3-Statement Model net PP&E | C65: =C63-'3-Statement Model'!C51 -> 0

Sheet Segment and Margin Analysis
A1: McDonald's Corporation, Segment and Margin Analysis
A2: $ in millions. Segment figures per the FY2025 Form 10-K, Segment and Geographic Information note.
A3: This tab covers, in order: Segment Detail, Margin Bridge. Click column J, then use Ctrl+Down or Ctrl+Up to jump to each blue X marker, which sits on that section's header row.
A6: Segment Detail | J6: X
B8: FY2023 | C8: FY2024 | D8: FY2025
A9: Revenue by segment
A10: U.S. | B10: 10568 | C10: 10631 | D10: 10825
A11: International Operated Markets (IOM) | B11: 12382 | C11: 12628 | D11: 13633
A12: IDL & Corporate | B12: 2543 | C12: 2661 | D12: 2427
A13: Total segment revenue | B13: =SUM(B10:B12) -> 25493 | C13: =SUM(C10:C12) -> 25920 | D13: =SUM(D10:D12) -> 26885
A15: Operating income by segment
A16: U.S. | B16: 5694 | C16: 5733 | D16: 5808
A17: International Operated Markets (IOM) | B17: 5831 | C17: 5946 | D17: 6382
A18: IDL & Corporate | B18: 121 | C18: 33 | D18: 203
A19: Total segment operating income | B19: =SUM(B16:B18) -> 11646 | C19: =SUM(C16:C18) -> 11712 | D19: =SUM(D16:D18) -> 12393
A21: Segment operating margin
A22: U.S. | B22: =B16/B10 -> 0.53879637 | C22: =C16/C10 -> 0.53927194 | D22: =D16/D10 -> 0.5365358
A23: International Operated Markets (IOM) | B23: =B17/B11 -> 0.47092554 | C23: =C17/C11 -> 0.47085841 | D23: =D17/D11 -> 0.46812881
A24: IDL & Corporate | B24: =B18/B12 -> 0.047581597 | C24: =C18/C12 -> 0.012401353 | D24: =D18/D12 -> 0.083642357
A26: Tie-out: segment totals versus 3-Statement Model | D26: =D13-'3-Statement Model'!D13 -> 0
A27: Tie-out: segment operating income versus 3-Statement Model | D27: =D19-'3-Statement Model'!D24 -> 0
A40: Margin Bridge, Mix versus Rate Decomposition | J40: X
A41: Method: standard mix-rate variance decomposition, FY2024 to FY2025.
B43: Rev FY24 | C43: Rev FY25 | D43: Share FY24 | E43: Share FY25 | F43: Margin FY24 | G43: Margin FY25
A44: U.S. | B44: =C10 -> 10631 | C44: =D10 -> 10825 | D44: =B44/B$47 -> 0.4101466 | E44: =C44/C$47 -> 0.40264088 | F44: =C22 -> 0.53927194 | G44: =D22 -> 0.5365358
A45: International Operated Markets (IOM) | B45: =C11 -> 12628 | C45: =D11 -> 13633 | D45: =B45/B$47 -> 0.48719136 | E45: =C45/C$47 -> 0.50708574 | F45: =C23 -> 0.47085841 | G45: =D23 -> 0.46812881
A46: IDL & Corporate | B46: =C12 -> 2661 | C46: =D12 -> 2427 | D46: =B46/B$47 -> 0.10266204 | E46: =C46/C$47 -> 0.090273387 | F46: =C24 -> 0.012401353 | G46: =D24 -> 0.083642357
A47: Total | B47: =SUM(B44:B46) -> 25920 | C47: =SUM(C44:C46) -> 26885 | D47: =B47/B$47 -> 1 | E47: =C47/C$47 -> 1 | F47: =C19/C13 -> 0.45185185 | G47: =D19/D13 -> 0.46096336
A49: Mix and rate effect, by segment
B50: Share change | C50: Mix effect | D50: Margin change | E50: Rate effect
A51: U.S. | B51: =E44-D44 -> -0.0075057271 | C51: =B51*F44 -> -0.004047628 | D51: =G44-F44 -> -0.0027361438 | E51: =E44*D51 -> -0.0011016833
A52: International Operated Markets (IOM) | B52: =E45-D45 -> 0.019894378 | C52: =B52*F45 -> 0.009367435 | D52: =G45-F45 -> -0.0027296048 | E52: =E45*D52 -> -0.0013841436
A53: IDL & Corporate | B53: =E46-D46 -> -0.01238865 | C53: =B53*F46 -> -0.00015363603 | D53: =G46-F46 -> 0.071241004 | E53: =E46*D53 -> 0.0064311667
A54: Total | C54: =SUM(C51:C53) -> 0.0051661709 | E54: =SUM(E51:E53) -> 0.0039453397
A56: Reconciliation
A57: Overall margin, FY2024 | B57: =F47 -> 0.45185185
A58: Overall margin, FY2025 | B58: =G47 -> 0.46096336
A59: Total change, actual | B59: =B58-B57 -> 0.0091115106
A60: Total mix and rate effect, from the table above | B60: =C54+E54 -> 0.0091115106
A61: Reconciliation check | B61: =B59-B60 -> 9.7144515e-17
A63: Reading the result
A64: Overall operating margin rose 0.9 points to 46.1% in FY2025. The two largest segments moved for
A65: different reasons. IOM contributed the largest single effect, nearly all of it from mix, its revenue
A66: share grew from 48.7% to 50.7% of the total at a broadly stable margin. IDL & Corporate contributed
A67: the second-largest effect almost entirely from rate, its own margin rose from 1.2% to 8.4% even as
A68: its revenue share shrank. The U.S. was a modest drag on both dimensions.
A70: In short: the segment growing fastest and the segment getting more profitable are not the same
A71: segment, and the two effects are roughly the same size.
A73: Waterfall chart data
A74: Step | B74: Base | C74: Decrease | D74: Increase | E74: Total
A75: FY2024 margin | B75: 0 | C75: 0 | D75: 0 | E75: =B57 -> 0.45185185 | F75: =B57 -> 0.45185185
A76: U.S. mix | B76: =MIN(F75,F75+C51) -> 0.44780422 | C76: =IF(C51<0,ABS(C51),0) -> 0.004047628 | D76: =IF(C51>=0,ABS(C51),0) -> 0 | E76: 0 | F76: =F75+C51 -> 0.44780422
A77: U.S. rate | B77: =MIN(F76,F76+E51) -> 0.44670254 | C77: =IF(E51<0,ABS(E51),0) -> 0.0011016833 | D77: =IF(E51>=0,ABS(E51),0) -> 0 | E77: 0 | F77: =F76+E51 -> 0.44670254
A78: IOM mix | B78: =MIN(F77,F77+C52) -> 0.44670254 | C78: =IF(C52<0,ABS(C52),0) -> 0 | D78: =IF(C52>=0,ABS(C52),0) -> 0.009367435 | E78: 0 | F78: =F77+C52 -> 0.45606998
A79: IOM rate | B79: =MIN(F78,F78+E52) -> 0.45468583 | C79: =IF(E52<0,ABS(E52),0) -> 0.0013841436 | D79: =IF(E52>=0,ABS(E52),0) -> 0 | E79: 0 | F79: =F78+E52 -> 0.45468583
A80: IDL mix | B80: =MIN(F79,F79+C53) -> 0.4545322 | C80: =IF(C53<0,ABS(C53),0) -> 0.00015363603 | D80: =IF(C53>=0,ABS(C53),0) -> 0 | E80: 0 | F80: =F79+C53 -> 0.4545322
A81: IDL rate | B81: =MIN(F80,F80+E53) -> 0.4545322 | C81: =IF(E53<0,ABS(E53),0) -> 0 | D81: =IF(E53>=0,ABS(E53),0) -> 0.0064311667 | E81: 0 | F81: =F80+E53 -> 0.46096336
A82: FY2025 margin | B82: 0 | C82: 0 | D82: 0 | E82: =B58 -> 0.46096336 | F82: =B58 -> 0.46096336

Sheet Valuation
A1: McDonald's Corporation, Valuation
A2: $ in millions, except per-share data.
A3: This tab covers, in order: WACC Build, DCF Valuation. Click column J, then use Ctrl+Down or Ctrl+Up to jump to each blue X marker, which sits on that section's header row.
A6: WACC Build | J6: X
A8: Cost of equity, CAPM
A9: Risk-free rate, 10-year U.S. Treasury yield | B9: 0.0479
A10: Beta | B10: 0.6
A11: Equity risk premium, implied, U.S. | B11: 0.0445
A12: Cost of equity | B12: =B9+B10*B11 -> 0.0746
A14: Cost of debt
A15: Pre-tax cost of debt | B15: 0.045
A16: Effective tax rate | B16: ='3-Statement Model'!D30/'3-Statement Model'!D28 -> 0.21416774
A17: After-tax cost of debt | B17: =B15*(1-B16) -> 0.035362452
A19: Capital structure weights
A20: Shares outstanding, millions | B20: 711
A21: Share price | B21: 307
A22: Market value of equity | B22: =B20*B21 -> 218277
A23: Total debt, book value | B23: ='3-Statement Model'!C56 -> 39973
A24: Total capital | B24: =B22+B23 -> 258250
A25: Weight of equity | B25: =B22/B24 -> 0.84521588
A26: Weight of debt | B26: =B23/B24 -> 0.15478412
A28: WACC, base case | B28: =B25*B12+B26*B17 -> 0.06852665
A30: Every input above involves judgment. Beta and the cost of debt in particular are estimated,
A31: not observed, which is why the DCF below tests a range of WACC values rather than relying on a single point.
A35: DCF Valuation, 5-Year Explicit Forecast Plus Terminal Value | J35: X
A37: Key assumptions
A38: Revenue growth, year 1 | B38: 0.045
A39: Revenue growth, annual taper | B39: -0.0025
A40: Operating margin, held at FY2025 level | B40: ='3-Statement Model'!D33 -> 0.46096336
A41: Effective tax rate | B41: =B16 -> 0.21416774
A42: D&A, percent of revenue | B42: ='3-Statement Model'!D19/'3-Statement Model'!D13 -> 0.016998326
A43: Capital expenditures, percent of revenue | B43: =-'3-Statement Model'!C80/'3-Statement Model'!D13 -> 0.12516273
A44: Change in net working capital, percent of revenue | B44: 0
A45: WACC | B45: =B28 -> 0.06852665
A46: Terminal growth rate | B46: 0.025
A48: Free cash flow projection
B49: FY2025A | C49: FY2026E | D49: FY2027E | E49: FY2028E | F49: FY2029E | G49: FY2030E
A50: Revenue growth rate | C50: =$B$38 -> 0.045 | D50: =C50+$B$39 -> 0.0425 | E50: =D50+$B$39 -> 0.04 | F50: =E50+$B$39 -> 0.0375 | G50: =F50+$B$39 -> 0.035
A51: Revenue | B51: ='3-Statement Model'!D13 -> 26885 | C51: =B51*(1+C50) -> 28094.825 | D51: =C51*(1+D50) -> 29288.855 | E51: =D51*(1+E50) -> 30460.409 | F51: =E51*(1+F50) -> 31602.675 | G51: =F51*(1+G50) -> 32708.768
A52: Operating income | B52: =B51*$B$40 -> 12393 | C52: =C51*$B$40 -> 12950.685 | D52: =D51*$B$40 -> 13501.089 | E52: =E51*$B$40 -> 14041.133 | F52: =F51*$B$40 -> 14567.675 | G52: =G51*$B$40 -> 15077.544
A53: Less, taxes on operating income | B53: =B52*$B$41 -> 2654.1808 | C53: =C52*$B$41 -> 2773.6189 | D53: =D52*$B$41 -> 2891.4977 | E53: =E52*$B$41 -> 3007.1576 | F53: =F52*$B$41 -> 3119.926 | G53: =G52*$B$41 -> 3229.1234
A54: NOPAT | B54: =B52-B53 -> 9738.8192 | C54: =C52-C53 -> 10177.066 | D54: =D52-D53 -> 10609.591 | E54: =E52-E53 -> 11033.975 | F54: =F52-F53 -> 11447.749 | G54: =G52-G53 -> 11848.42
A55: Add back, D&A | B55: =B51*$B$42 -> 457 | C55: =C51*$B$42 -> 477.565 | D55: =D51*$B$42 -> 497.86151 | E55: =E51*$B$42 -> 517.77597 | F55: =F51*$B$42 -> 537.19257 | G55: =G51*$B$42 -> 555.99431
A56: Less, capital expenditures | B56: =B51*$B$43 -> 3365 | C56: =C51*$B$43 -> 3516.425 | D56: =D51*$B$43 -> 3665.8731 | E56: =E51*$B$43 -> 3812.508 | F56: =F51*$B$43 -> 3955.477 | G56: =G51*$B$43 -> 4093.9187
A57: Less, increase in net working capital | B57: =B51*$B$44 -> 0 | C57: =C51*$B$44 -> 0 | D57: =D51*$B$44 -> 0 | E57: =E51*$B$44 -> 0 | F57: =F51*$B$44 -> 0 | G57: =G51*$B$44 -> 0
A58: Unlevered free cash flow | B58: =B54+B55-B56-B57 -> 6830.8192 | C58: =C54+C55-C56-C57 -> 7138.2061 | D58: =D54+D55-D56-D57 -> 7441.5799 | E58: =E54+E55-E56-E57 -> 7739.2431 | F58: =F54+F55-F56-F57 -> 8029.4647 | G58: =G54+G55-G56-G57 -> 8310.4959
A60: Discounting and terminal value
A61: Discount period, years | C61: 1 | D61: 2 | E61: 3 | F61: 4 | G61: 5
A62: Discount factor | C62: =1/(1+$B$45)^C61 -> 0.93586809 | D62: =1/(1+$B$45)^D61 -> 0.87584909 | E62: =1/(1+$B$45)^E61 -> 0.81967922 | F62: =1/(1+$B$45)^F61 -> 0.76711163 | G62: =1/(1+$B$45)^G61 -> 0.7179153
A63: Present value of free cash flow | C63: =C58*C62 -> 6680.4193 | D63: =D58*D62 -> 6517.7009 | E63: =E58*E62 -> 6343.6967 | F63: =F58*F62 -> 6159.4957 | G63: =G58*G62 -> 5966.2322
A65: Sum of present value, years 1 to 5 | B65: =SUM(C63:G63) -> 31667.545
A67: Terminal year free cash flow | B67: =G58*(1+$B$46) -> 8518.2583
A68: Terminal value | B68: =B67/($B$45-$B$46) -> 195702.13
A69: Present value of terminal value | B69: =B68*G62 -> 140497.55
A71: Implied enterprise value | B71: =B65+B69 -> 172165.1
A72: Percent of value from terminal value | B72: =B69/B71 -> 0.81606292
A74: Bridge to equity value and implied share price
A75: Less, total debt | B75: =-'3-Statement Model'!C56 -> -39973
A76: Add, cash and equivalents | B76: ='3-Statement Model'!C44 -> 774
A77: Implied equity value | B77: =B71+B75+B76 -> 132966.1
A78: Diluted shares outstanding, millions | B78: 716.4
A79: Implied share price | B79: =B77/B78 -> 185.60315
A80: Market price | B80: =B21 -> 307
A81: Implied upside, downside, versus market | B81: =B79/B80-1 -> -0.39542947
A83: Sensitivity: enterprise value across WACC and terminal growth rate
A84: Each cell independently recomputes the five-year cash flow and terminal value at that pair.
A86: EV ($mm) | B86: 0.015 | C86: 0.02 | D86: 0.025 | E86: 0.03 | F86: 0.035
A87: 0.0585 | B87: =C58/(1+0.0585)^1+D58/(1+0.0585)^2+E58/(1+0.0585)^3+F58/(1+0.0585)^4+G58/(1+0.0585)^5+((G58*(1+0.015))/(0.0585-0.015))/(1+0.0585)^5 -> 178493.2 | C87: =C58/(1+0.0585)^1+D58/(1+0.0585)^2+E58/(1+0.0585)^3+F58/(1+0.0585)^4+G58/(1+0.0585)^5+((G58*(1+0.02))/(0.0585-0.02))/(1+0.0585)^5 -> 198257.59 | D87: =C58/(1+0.0585)^1+D58/(1+0.0585)^2+E58/(1+0.0585)^3+F58/(1+0.0585)^4+G58/(1+0.0585)^5+((G58*(1+0.025))/(0.0585-0.025))/(1+0.0585)^5 -> 223921.81 | E87: =C58/(1+0.0585)^1+D58/(1+0.0585)^2+E58/(1+0.0585)^3+F58/(1+0.0585)^4+G58/(1+0.0585)^5+((G58*(1+0.03))/(0.0585-0.03))/(1+0.0585)^5 -> 258591.01 | F87: =C58/(1+0.0585)^1+D58/(1+0.0585)^2+E58/(1+0.0585)^3+F58/(1+0.0585)^4+G58/(1+0.0585)^5+((G58*(1+0.035))/(0.0585-0.035))/(1+0.0585)^5 -> 308013.06
A88: 0.0635 | B88: =C58/(1+0.0635)^1+D58/(1+0.0635)^2+E58/(1+0.0635)^3+F58/(1+0.0635)^4+G58/(1+0.0635)^5+((G58*(1+0.015))/(0.0635-0.015))/(1+0.0635)^5 -> 159949.99 | C88: =C58/(1+0.0635)^1+D58/(1+0.0635)^2+E58/(1+0.0635)^3+F58/(1+0.0635)^4+G58/(1+0.0635)^5+((G58*(1+0.02))/(0.0635-0.02))/(1+0.0635)^5 -> 175346.28 | D88: =C58/(1+0.0635)^1+D58/(1+0.0635)^2+E58/(1+0.0635)^3+F58/(1+0.0635)^4+G58/(1+0.0635)^5+((G58*(1+0.025))/(0.0635-0.025))/(1+0.0635)^5 -> 194741.6 | E88: =C58/(1+0.0635)^1+D58/(1+0.0635)^2+E58/(1+0.0635)^3+F58/(1+0.0635)^4+G58/(1+0.0635)^5+((G58*(1+0.03))/(0.0635-0.03))/(1+0.0635)^5 -> 219926.57 | F88: =C58/(1+0.0635)^1+D58/(1+0.0635)^2+E58/(1+0.0635)^3+F58/(1+0.0635)^4+G58/(1+0.0635)^5+((G58*(1+0.035))/(0.0635-0.035))/(1+0.0635)^5 -> 253948.37
A89: 0.0685 | B89: =C58/(1+0.0685)^1+D58/(1+0.0685)^2+E58/(1+0.0685)^3+F58/(1+0.0685)^4+G58/(1+0.0685)^5+((G58*(1+0.015))/(0.0685-0.015))/(1+0.0685)^5 -> 144875.12 | C89: =C58/(1+0.0685)^1+D58/(1+0.0685)^2+E58/(1+0.0685)^3+F58/(1+0.0685)^4+G58/(1+0.0685)^5+((G58*(1+0.02))/(0.0685-0.02))/(1+0.0685)^5 -> 157160.92 | D89: =C58/(1+0.0685)^1+D58/(1+0.0685)^2+E58/(1+0.0685)^3+F58/(1+0.0685)^4+G58/(1+0.0685)^5+((G58*(1+0.025))/(0.0685-0.025))/(1+0.0685)^5 -> 172271.03 | E89: =C58/(1+0.0685)^1+D58/(1+0.0685)^2+E58/(1+0.0685)^3+F58/(1+0.0685)^4+G58/(1+0.0685)^5+((G58*(1+0.03))/(0.0685-0.03))/(1+0.0685)^5 -> 191305.86 | F89: =C58/(1+0.0685)^1+D58/(1+0.0685)^2+E58/(1+0.0685)^3+F58/(1+0.0685)^4+G58/(1+0.0685)^5+((G58*(1+0.035))/(0.0685-0.035))/(1+0.0685)^5 -> 216022.72
A90: 0.0735 | B90: =C58/(1+0.0735)^1+D58/(1+0.0735)^2+E58/(1+0.0735)^3+F58/(1+0.0735)^4+G58/(1+0.0735)^5+((G58*(1+0.015))/(0.0735-0.015))/(1+0.0735)^5 -> 132379.22 | C90: =C58/(1+0.0735)^1+D58/(1+0.0735)^2+E58/(1+0.0735)^3+F58/(1+0.0735)^4+G58/(1+0.0735)^5+((G58*(1+0.02))/(0.0735-0.02))/(1+0.0735)^5 -> 142376.43 | D90: =C58/(1+0.0735)^1+D58/(1+0.0735)^2+E58/(1+0.0735)^3+F58/(1+0.0735)^4+G58/(1+0.0735)^5+((G58*(1+0.025))/(0.0735-0.025))/(1+0.0735)^5 -> 154434.93 | E90: =C58/(1+0.0735)^1+D58/(1+0.0735)^2+E58/(1+0.0735)^3+F58/(1+0.0735)^4+G58/(1+0.0735)^5+((G58*(1+0.03))/(0.0735-0.03))/(1+0.0735)^5 -> 169265.5 | F90: =C58/(1+0.0735)^1+D58/(1+0.0735)^2+E58/(1+0.0735)^3+F58/(1+0.0735)^4+G58/(1+0.0735)^5+((G58*(1+0.035))/(0.0735-0.035))/(1+0.0735)^5 -> 187948.16
A91: 0.0785 | B91: =C58/(1+0.0785)^1+D58/(1+0.0785)^2+E58/(1+0.0785)^3+F58/(1+0.0785)^4+G58/(1+0.0785)^5+((G58*(1+0.015))/(0.0785-0.015))/(1+0.0785)^5 -> 121853.03 | C91: =C58/(1+0.0785)^1+D58/(1+0.0785)^2+E58/(1+0.0785)^3+F58/(1+0.0785)^4+G58/(1+0.0785)^5+((G58*(1+0.02))/(0.0785-0.02))/(1+0.0785)^5 -> 130120.77 | D91: =C58/(1+0.0785)^1+D58/(1+0.0785)^2+E58/(1+0.0785)^3+F58/(1+0.0785)^4+G58/(1+0.0785)^5+((G58*(1+0.025))/(0.0785-0.025))/(1+0.0785)^5 -> 139933.88 | E91: =C58/(1+0.0785)^1+D58/(1+0.0785)^2+E58/(1+0.0785)^3+F58/(1+0.0785)^4+G58/(1+0.0785)^5+((G58*(1+0.03))/(0.0785-0.03))/(1+0.0785)^5 -> 151770.31 | F91: =C58/(1+0.0785)^1+D58/(1+0.0785)^2+E58/(1+0.0785)^3+F58/(1+0.0785)^4+G58/(1+0.0785)^5+((G58*(1+0.035))/(0.0785-0.035))/(1+0.0785)^5 -> 166327.77
A93: Rows: WACC. Columns: terminal growth rate. Highlighted cell: base case.
A95: Reading the result
A96: This DCF implies a value below McDonald's actual trading price, for three reasons worth stating
A97: plainly rather than explaining away: it does not model the effect of continued share buybacks on
A98: share count, WACC and terminal growth here are reasoned estimates rather than directly observed
A99: market figures, and a DCF built from first principles is not expected to match market price exactly,
A100: that is the point of building one. The base case sits centrally within the tested sensitivity range,
A101: not at an edge, which is itself a reasonable check on the assumptions.

Sheet StagingData
A1: Quarter | B1: Line Item | C1: Value
A2: Q2 2026 | B2: Company-owned and operated restaurant expenses | C2: 2138
A3: Q2 2026 | B3: Franchised restaurants-occupancy expenses | C3: 680
A4: Q2 2026 | B4: Income before provision for income taxes | C4: 2936
A5: Q2 2026 | B5: Interest expense | C5: 409
A6: Q2 2026 | B6: Net income | C6: 2362
A7: Q2 2026 | B7: Nonoperating (income) expense, net | C7: -6
A8: Q2 2026 | B8: Operating income | C8: 3338
A9: Q2 2026 | B9: Other operating (income) expense, net | C9: -37
A10: Q2 2026 | B10: Other restaurant expenses | C10: 163
A11: Q2 2026 | B11: Other revenues | C11: 182
A12: Q2 2026 | B12: Provision for income taxes | C12: 574
A13: Q2 2026 | B13: Revenues from franchised restaurants | C13: 4393
... A18: Q2 2026 | B18: Total revenues | C18: 7099

Sheet PQ Staging
A1: Quarterly Data Staging Area
A2: Each quarter, paste the new quarter's income statement figures below, then refresh the Power Query connection.
A4: Quarter label
A5: Q2 2026
A7: Line Item | B7: This Quarter | C7: Prior-Year Quarter
A8: Revenues from franchised restaurants | B8: 4393 | C8: 4213
A9: Sales by Company-owned and operated restaurants | B9: 2525 | C9: 2458
A10: Other revenues | B10: 182 | C10: 172
A11: Total revenues | B11: 7099 | C11: 6843
A12: Franchised restaurants-occupancy expenses | B12: 680 | C12: 654
A13: Company-owned and operated restaurant expenses | B13: 2138 | C13: 2078
A14: Other restaurant expenses | B14: 163 | C14: 149
A15: SG&A - Depreciation and amortization | B15: 111 | C15: 106
A16: SG&A - Other | B16: 706 | C16: 595
A17: Other operating (income) expense, net | B17: -37 | C17: 29
A18: Total operating costs and expenses | B18: 3760 | C18: 3611
A19: Operating income | B19: 3338 | C19: 3232
... A24: Net income | B24: 2362 | C24: 2253
A27: Quarter history log
A28: Quarter | B28: Total Revenue | C28: Operating Income | D28: Net Income
A29: Q4 2025 | B29: 7009 | C29: 3156 | D29: 2164
A30: Q1 2026 | B30: 6517 | C30: 2953 | D30: 1980
A31: Q2 2026 | B31: 7099 | C31: 3338 | D31: 2362

Sheet Power BI Source Data
A1: Power BI Source Data
A2: Clean, tidy tables, linked live to the rest of this workbook, for the Power BI dashboard.
A5: Income Statement Trend
A7: Year | B7: Revenue | C7: OperatingIncome | D7: NetIncome | E7: OperatingMargin | F7: FranchisedRevenue | G7: CompanyOperatedRevenue | H7: OtherRevenue
A8: FY2023 | B8: ='3-Statement Model'!B13 -> 25495 | C8: ='3-Statement Model'!B24 -> 11648 | D8: ='3-Statement Model'!B31 -> 8470 | E8: ='3-Statement Model'!B33 -> 0.4568739 | F8: ='3-Statement Model'!B10 -> 15437 | G8: ='3-Statement Model'!B11 -> 9742 | H8: ='3-Statement Model'!B12 -> 316
A9: FY2024 | B9: ='3-Statement Model'!C13 -> 25920 | C9: ='3-Statement Model'!C24 -> 11713 | D9: ='3-Statement Model'!C31 -> 8225 | E9: ='3-Statement Model'!C33 -> 0.45189043 | F9: ='3-Statement Model'!C10 -> 15715 | G9: ='3-Statement Model'!C11 -> 9782 | H9: ='3-Statement Model'!C12 -> 423
A10: FY2025 | B10: ='3-Statement Model'!D13 -> 26885 | C10: ='3-Statement Model'!D24 -> 12393 | D10: ='3-Statement Model'!D31 -> 8564 | E10: ='3-Statement Model'!D33 -> 0.46096336 | F10: ='3-Statement Model'!D10 -> 16548 | G10: ='3-Statement Model'!D11 -> 9690 | H10: ='3-Statement Model'!D12 -> 647
A13: Segment Performance
A15: Segment | B15: Year | C15: Revenue | D15: OperatingIncome | E15: Margin
A16: U.S. | B16: FY2024 | C16: ='Segment and Margin Analysis'!C10 -> 10631 | D16: ='Segment and Margin Analysis'!C16 -> 5733 | E16: ='Segment and Margin Analysis'!C22 -> 0.53927194
A17: U.S. | B17: FY2025 | C17: ='Segment and Margin Analysis'!D10 -> 10825 | D17: ='Segment and Margin Analysis'!D16 -> 5808 | E17: ='Segment and Margin Analysis'!D22 -> 0.5365358
A18: International Operated Markets (IOM) | B18: FY2024 | C18: ='Segment and Margin Analysis'!C11 -> 12628 | D18: ='Segment and Margin Analysis'!C17 -> 5946 | E18: ='Segment and Margin Analysis'!C23 -> 0.47085841
A19: International Operated Markets (IOM) | B19: FY2025 | C19: ='Segment and Margin Analysis'!D11 -> 13633 | D19: ='Segment and Margin Analysis'!D17 -> 6382 | E19: ='Segment and Margin Analysis'!D23 -> 0.46812881
A20: IDL & Corporate | B20: FY2024 | C20: ='Segment and Margin Analysis'!C12 -> 2661 | D20: ='Segment and Margin Analysis'!C18 -> 33 | E20: ='Segment and Margin Analysis'!C24 -> 0.012401353
A21: IDL & Corporate | B21: FY2025 | C21: ='Segment and Margin Analysis'!D12 -> 2427 | D21: ='Segment and Margin Analysis'!D18 -> 203 | E21: ='Segment and Margin Analysis'!D24 -> 0.083642357
A24: Margin Bridge Waterfall Data
A26: Segment | B26: MixEffect | C26: RateEffect
A27: U.S. | B27: ='Segment and Margin Analysis'!C51 -> -0.004047628 | C27: ='Segment and Margin Analysis'!E51 -> -0.0011016833
A28: International Operated Markets (IOM) | B28: ='Segment and Margin Analysis'!C52 -> 0.009367435 | C28: ='Segment and Margin Analysis'!E52 -> -0.0013841436
A29: IDL & Corporate | B29: ='Segment and Margin Analysis'!C53 -> -0.00015363603 | C29: ='Segment and Margin Analysis'!E53 -> 0.0064311667
A32: DCF Valuation Summary
A34: Metric | B34: Value
A35: Enterprise Value | B35: =Valuation!B71 -> 172165.1
A36: Implied Share Price | B36: =Valuation!B79 -> 185.60315
A37: Market Price | B37: =Valuation!B80 -> 307
A38: WACC | B38: =Valuation!B45 -> 0.06852665
A39: Terminal Growth Rate | B39: =Valuation!B46 -> 0.025
A40: Upside Downside | B40: =Valuation!B81 -> -0.39542947
A43: WACC | B43: TerminalGrowth | C43: EnterpriseValue
A44: =Valuation!A87 -> 0.0585 | B44: =Valuation!B86 -> 0.015 | C44: =Valuation!B87 -> 178493.2
A45: =Valuation!A87 -> 0.0585 | B45: =Valuation!C86 -> 0.02 | C45: =Valuation!C87 -> 198257.59
A46: =Valuation!A87 -> 0.0585 | B46: =Valuation!D86 -> 0.025 | C46: =Valuation!D87 -> 223921.81
A47: =Valuation!A87 -> 0.0585 | B47: =Valuation!E86 -> 0.03 | C47: =Valuation!E87 -> 258591.01
A48: =Valuation!A87 -> 0.0585 | B48: =Valuation!F86 -> 0.035 | C48: =Valuation!F87 -> 308013.06
A49: =Valuation!A88 -> 0.0635 | B49: =Valuation!B86 -> 0.015 | C49: =Valuation!B88 -> 159949.99
A50: =Valuation!A88 -> 0.0635 | B50: =Valuation!C86 -> 0.02 | C50: =Valuation!C88 -> 175346.28
A51: =Valuation!A88 -> 0.0635 | B51: =Valuation!D86 -> 0.025 | C51: =Valuation!D88 -> 194741.6
A52: =Valuation!A88 -> 0.0635 | B52: =Valuation!E86 -> 0.03 | C52: =Valuation!E88 -> 219926.57
A53: =Valuation!A88 -> 0.0635 | B53: =Valuation!F86 -> 0.035 | C53: =Valuation!F88 -> 253948.37
A54: =Valuation!A89 -> 0.0685 | B54: =Valuation!B86 -> 0.015 | C54: =Valuation!B89 -> 144875.12
A55: =Valuation!A89 -> 0.0685 | B55: =Valuation!C86 -> 0.02 | C55: =Valuation!C89 -> 157160.92
A56: =Valuation!A89 -> 0.0685 | B56: =Valuation!D86 -> 0.025 | C56: =Valuation!D89 -> 172271.03
A57: =Valuation!A89 -> 0.0685 | B57: =Valuation!E86 -> 0.03 | C57: =Valuation!E89 -> 191305.86
A58: =Valuation!A89 -> 0.0685 | B58: =Valuation!F86 -> 0.035 | C58: =Valuation!F89 -> 216022.72
A59: =Valuation!A90 -> 0.0735 | B59: =Valuation!B86 -> 0.015 | C59: =Valuation!B90 -> 132379.22
A60: =Valuation!A90 -> 0.0735 | B60: =Valuation!C86 -> 0.02 | C60: =Valuation!C90 -> 142376.43
A61: =Valuation!A90 -> 0.0735 | B61: =Valuation!D86 -> 0.025 | C61: =Valuation!D90 -> 154434.93
A62: =Valuation!A90 -> 0.0735 | B62: =Valuation!E86 -> 0.03 | C62: =Valuation!E90 -> 169265.5
A63: =Valuation!A90 -> 0.0735 | B63: =Valuation!F86 -> 0.035 | C63: =Valuation!F90 -> 187948.16
A64: =Valuation!A91 -> 0.0785 | B64: =Valuation!B86 -> 0.015 | C64: =Valuation!B91 -> 121853.03
A65: =Valuation!A91 -> 0.0785 | B65: =Valuation!C86 -> 0.02 | C65: =Valuation!C91 -> 130120.77
A66: =Valuation!A91 -> 0.0785 | B66: =Valuation!D86 -> 0.025 | C66: =Valuation!D91 -> 139933.88
A67: =Valuation!A91 -> 0.0785 | B67: =Valuation!E86 -> 0.03 | C67: =Valuation!E91 -> 151770.31
A68: =Valuation!A91 -> 0.0785 | B68: =Valuation!F86 -> 0.035 | C68: =Valuation!F91 -> 166327.77
